.DS_Store
breakout_game/__init__.py
breakout_game/game.py
taichi_breakout_game-0.1.1.dist-info/METADATA
taichi_breakout_game-0.1.1.dist-info/WHEEL
taichi_breakout_game-0.1.1.dist-info/entry_points.txt
taichi_breakout_game-0.1.1.dist-info/top_level.txt
taichi_breakout_game-0.1.1.dist-info/RECORD
